PgCognition/Cognito.py
PgCognition/DatabaseClient.py
PgCognition/__init__.py
PgCognition/cognition_functions.py
PgCognition/Schema/Builder.py
PgCognition/Schema/CloneSchema.py
PgCognition/Schema/CreateRoleFunction.py
PgCognition/Schema/GetTenantsFunction.py
PgCognition/Schema/Grants.py
PgCognition/Schema/GroupsOfFunction.py
PgCognition/Schema/RLS.py
PgCognition/Schema/StepdownFunction.py
PgCognition/Schema/TenantRoleFunction.py
PgCognition/Schema/TenantsTable.py
PgCognition/Schema/UsersTable.py
PgCognition/Schema/__init__.py
pg_cognition-0.0.19.dist-info/LICENSE
pg_cognition-0.0.19.dist-info/METADATA
pg_cognition-0.0.19.dist-info/WHEEL
pg_cognition-0.0.19.dist-info/top_level.txt
pg_cognition-0.0.19.dist-info/RECORD
