Metadata-Version: 2.1
Name: pg-cognition
Version: 0.0.19
Summary: Building blocks for a Postgres + Appsync + Cognito framework
Home-page: https://github.com/QuiNovas/pg-cognition
Author: Mathew Moon
Author-email: mmoon@quinovas.com
License: Apache 2.0
Platform: UNKNOWN
Classifier: Development Status :: 3 - Alpha
Classifier: Intended Audience :: Developers
Classifier: License :: OSI Approved :: Apache Software License
Classifier: Programming Language :: Python :: 3.7
Requires-Dist: aurora-prettyparser
Requires-Dist: psycopg2-binary
Requires-Dist: boto3
Requires-Dist: botocore
